wow_ai_vision/__init__.py
wow_ai_vision/annotators/__init__.py
wow_ai_vision/annotators/base.py
wow_ai_vision/annotators/core.py
wow_ai_vision/annotators/utils.py
wow_ai_vision/classification/__init__.py
wow_ai_vision/classification/core.py
wow_ai_vision/dataset/__init__.py
wow_ai_vision/dataset/core.py
wow_ai_vision/dataset/formats/__init__.py
wow_ai_vision/dataset/formats/coco.py
wow_ai_vision/dataset/formats/pascal_voc.py
wow_ai_vision/dataset/formats/yolo.py
wow_ai_vision/dataset/utils.py
wow_ai_vision/detection/__init__.py
wow_ai_vision/detection/annotate.py
wow_ai_vision/detection/core.py
wow_ai_vision/detection/line_counter.py
wow_ai_vision/detection/tools/__init__.py
wow_ai_vision/detection/tools/inference_slicer.py
wow_ai_vision/detection/tools/polygon_zone.py
wow_ai_vision/detection/utils.py
wow_ai_vision/draw/__init__.py
wow_ai_vision/draw/color.py
wow_ai_vision/draw/utils.py
wow_ai_vision/geometry/__init__.py
wow_ai_vision/geometry/core.py
wow_ai_vision/geometry/utils.py
wow_ai_vision/metrics/__init__.py
wow_ai_vision/metrics/detection.py
wow_ai_vision/tracker/__init__.py
wow_ai_vision/tracker/byte_tracker/__init__.py
wow_ai_vision/tracker/byte_tracker/basetrack.py
wow_ai_vision/tracker/byte_tracker/core.py
wow_ai_vision/tracker/byte_tracker/kalman_filter.py
wow_ai_vision/tracker/byte_tracker/matching.py
wow_ai_vision/utils/__init__.py
wow_ai_vision/utils/file.py
wow_ai_vision/utils/image.py
wow_ai_vision/utils/internal.py
wow_ai_vision/utils/notebook.py
wow_ai_vision/utils/video.py
wow_ai_vision-0.0.4.dist-info/LICENSE.md
wow_ai_vision-0.0.4.dist-info/METADATA
wow_ai_vision-0.0.4.dist-info/WHEEL
wow_ai_vision-0.0.4.dist-info/RECORD
