Metadata-Version: 2.1
Name: wow-ai-vision
Version: 0.0.4
Summary: A set of easy-to-use utils that will come in handy in any Computer Vision project
Home-page: https://github.com/wow-ai/wow_ai_vision
License: MIT
Keywords: machine-learning,deep-learning,vision,ML,DL,AI,YOLOv5,YOLOv8,SAM
Author: huonghx
Author-email: huonghx@wow-ai.com
Maintainer: huonghx
Maintainer-email: huonghx@wow-ai.com
Requires-Python: >=3.8,<3.12.0
Classifier: Development Status :: 4 - Beta
Classifier: Intended Audience :: Developers
Classifier: Intended Audience :: Education
Classifier: Intended Audience :: Science/Research
Classifier: License :: OSI Approved :: MIT License
Classifier: Operating System :: MacOS
Classifier: Operating System :: Microsoft :: Windows
Classifier: Operating System :: POSIX :: Linux
Classifier: Programming Language :: Python :: 3
Classifier: Programming Language :: Python :: 3.8
Classifier: Programming Language :: Python :: 3.9
Classifier: Programming Language :: Python :: 3.10
Classifier: Programming Language :: Python :: 3.11
Classifier: Programming Language :: Python :: 3 :: Only
Classifier: Topic :: Scientific/Engineering
Classifier: Topic :: Scientific/Engineering :: Artificial Intelligence
Classifier: Topic :: Scientific/Engineering :: Image Recognition
Classifier: Topic :: Software Development
Classifier: Typing :: Typed
Provides-Extra: desktop
Requires-Dist: matplotlib (>=3.7.1,<4.0.0)
Requires-Dist: numpy (>=1.20.0,<2.0.0)
Requires-Dist: opencv-python (>=4.8.0.74,<5.0.0.0) ; extra == "desktop"
Requires-Dist: opencv-python-headless (>=4.8.0.74,<5.0.0.0)
Requires-Dist: pillow (>=9.4,<11.0)
Requires-Dist: pyyaml (>=6.0,<7.0)
Requires-Dist: scipy (>=1.9.0,<2.0.0)
Project-URL: Documentation, https://github.com/wow-ai/wow_ai_vision/blob/main/README.md
Project-URL: Repository, https://github.com/wow-ai/wow_ai_vision
